deltametrics/__init__.py
deltametrics/_version.py
deltametrics/cube.py
deltametrics/io.py
deltametrics/mask.py
deltametrics/mobility.py
deltametrics/plan.py
deltametrics/plot.py
deltametrics/section.py
deltametrics/strat.py
deltametrics/utils.py
deltametrics/sample_data/__init__.py
deltametrics/sample_data/cube.py
deltametrics/sample_data/registry.txt
deltametrics/sample_data/sample_data.py
DeltaMetrics-0.4.0.dist-info/LICENSE.txt
DeltaMetrics-0.4.0.dist-info/METADATA
DeltaMetrics-0.4.0.dist-info/WHEEL
DeltaMetrics-0.4.0.dist-info/top_level.txt
DeltaMetrics-0.4.0.dist-info/RECORD
