Metadata-Version: 2.1
Name: DeltaMetrics
Version: 0.4.0
Summary: Tools for manipulating sedimentologic data cubes.
Home-page: https://github.com/DeltaRCM/DeltaMetrics
Author: The DeltaRCM Team
License: MIT
License-File: LICENSE.txt
Requires-Dist: matplotlib
Requires-Dist: netCDF4
Requires-Dist: h5netcdf
Requires-Dist: scipy
Requires-Dist: numpy
Requires-Dist: pyyaml
Requires-Dist: xarray
Requires-Dist: pooch
Requires-Dist: Shapely
Requires-Dist: scikit-image
Requires-Dist: numba
Requires-Dist: h5py
